scmcp_shared/__init__.py
scmcp_shared/agent.py
scmcp_shared/backend.py
scmcp_shared/cli.py
scmcp_shared/logging_config.py
scmcp_shared/mcp_base.py
scmcp_shared/util.py
scmcp_shared/kb/__init__.py
scmcp_shared/kb/_kb.py
scmcp_shared/kb/docs/workflow/decoupler_scRNA_Cell_Type_Annotation_Workflow.md
scmcp_shared/kb/docs/workflow/decoupler_scRNA_Pathway_Activity_Scoring_Workflow.md
scmcp_shared/kb/docs/workflow/decoupler_scRNA_TF_Activity_Scoring_Workflow.md
scmcp_shared/kb/docs/workflow/infercnv_CNV_tumor_identification_workflow.md
scmcp_shared/kb/docs/workflow/liana_ligand_receptor_communication_individual_methods_analysis.md
scmcp_shared/kb/docs/workflow/liana_ligand_receptor_communication_rank_aggregate_consensus.md
scmcp_shared/kb/docs/workflow/liana_ligand_receptor_communication_visualization_interpretation.md
scmcp_shared/schema/__init__.py
scmcp_shared/schema/io.py
scmcp_shared/schema/pl.py
scmcp_shared/schema/pp.py
scmcp_shared/schema/tl.py
scmcp_shared/schema/tool.py
scmcp_shared/schema/util.py
scmcp_shared/schema/preset/__init__.py
scmcp_shared/schema/preset/io.py
scmcp_shared/schema/preset/pl.py
scmcp_shared/schema/preset/pp.py
scmcp_shared/schema/preset/tl.py
scmcp_shared/schema/preset/util.py
scmcp_shared/server/__init__.py
scmcp_shared/server/auto.py
scmcp_shared/server/code.py
scmcp_shared/server/kb.py
scmcp_shared/server/rag.py
scmcp_shared/server/util.py
scmcp_shared/server/preset/__init__.py
scmcp_shared/server/preset/io.py
scmcp_shared/server/preset/pl.py
scmcp_shared/server/preset/pp.py
scmcp_shared/server/preset/tl.py
scmcp_shared/server/preset/util.py
scmcp_shared-0.6.5.dist-info/METADATA
scmcp_shared-0.6.5.dist-info/WHEEL
scmcp_shared-0.6.5.dist-info/licenses/LICENSE
scmcp_shared-0.6.5.dist-info/RECORD
