Metadata-Version: 2.4
Name: scmcp_shared
Version: 0.6.5
Summary: A shared function libray for scmcphub
Project-URL: Homepage, http://scmcphub.org/
Project-URL: Repository, https://github.com/scmcphub/scmcp-shared
Project-URL: Documentation, https://docs.scmcphub.org/
Author-email: shuang <hsh-me@outlook.com>
License: BSD 3-Clause License
License-File: LICENSE
Keywords: AI,agent,bioinformatics,llm,mcp,model context protocol,scRNA-seq,single cell
Requires-Python: >=3.10
Requires-Dist: abcoder
Requires-Dist: agno
Requires-Dist: fastmcp>=2.7.0
Requires-Dist: igraph
Requires-Dist: lancedb
Requires-Dist: leidenalg
Requires-Dist: mcp>=1.8.0
Requires-Dist: nest-asyncio
Requires-Dist: openai
Requires-Dist: requests
Requires-Dist: scanpy
